job_tqdflex/__init__.py
job_tqdflex/_version.py
job_tqdflex/parallel.py
job_tqdflex/version_helper.py
job_tqdflex-0.1.1.dist-info/licenses/LICENSE
job_tqdflex-0.1.1.dist-info/METADATA
job_tqdflex-0.1.1.dist-info/WHEEL
job_tqdflex-0.1.1.dist-info/top_level.txt
job_tqdflex-0.1.1.dist-info/RECORD
