Metadata-Version: 2.4
Name: job-tqdflex
Version: 0.1.1
Summary: Parallel processing with progress bars using joblib and tqdm
Author-email: David Araripe <david.araripe17@gmail.com>
License: CC-BY-SA-4.0
Project-URL: Homepage, https://github.com/yourusername/joblib-tqdm
Project-URL: Repository, https://github.com/yourusername/joblib-tqdm
Project-URL: Documentation, https://github.com/yourusername/joblib-tqdm#readme
Project-URL: Bug Tracker, https://github.com/yourusername/joblib-tqdm/issues
Keywords: parallel,processing,joblib,tqdm,progress,multiprocessing
Classifier: Development Status :: 4 - Beta
Classifier: Intended Audience :: Developers
Classifier: License :: CC0 1.0 Universal (CC0 1.0) Public Domain Dedication
Classifier: Operating System :: OS Independent
Classifier: Programming Language :: Python :: 3
Classifier: Programming Language :: Python :: 3.8
Classifier: Programming Language :: Python :: 3.9
Classifier: Programming Language :: Python :: 3.10
Classifier: Programming Language :: Python :: 3.11
Classifier: Programming Language :: Python :: 3.12
Classifier: Programming Language :: Python :: 3.13
Classifier: Programming Language :: Python :: 3.14
Classifier: Topic :: Software Development :: Libraries :: Python Modules
Classifier: Topic :: System :: Distributed Computing
Classifier: Topic :: Utilities
Requires-Python: >=3.8
License-File: LICENSE
Requires-Dist: joblib>=1.0.0
Requires-Dist: tqdm>=4.60.0
Provides-Extra: dev
Requires-Dist: pytest>=6.0; extra == "dev"
Requires-Dist: pytest-cov; extra == "dev"
Requires-Dist: black; extra == "dev"
Requires-Dist: isort; extra == "dev"
Requires-Dist: flake8; extra == "dev"
Requires-Dist: mypy; extra == "dev"
Requires-Dist: loguru>=0.6.0; extra == "dev"
Provides-Extra: test
Requires-Dist: pytest>=6.0; extra == "test"
Requires-Dist: pytest-cov; extra == "test"
Requires-Dist: pytest-mock; extra == "test"
Dynamic: license-file
